README.md
anotherpdfmerger.1
setup.py
anotherpdfmerger/__init__.py
anotherpdfmerger/anotherpdfmerger.py
anotherpdfmerger/version.py
anotherpdfmerger.egg-info/PKG-INFO
anotherpdfmerger.egg-info/SOURCES.txt
anotherpdfmerger.egg-info/dependency_links.txt
anotherpdfmerger.egg-info/entry_points.txt
anotherpdfmerger.egg-info/requires.txt
anotherpdfmerger.egg-info/top_level.txt