Metadata-Version: 1.1
Name: anotherpdfmerger
Version: 0.0.3
Summary: merge PDFs and generate bookmarks
Home-page: https://github.com/mwiens91/anotherpdfmerger
Author: Matt Wiens
Author-email: mwiens91@gmail.com
License: MIT
Platform: UNKNOWN
Classifier: Development Status :: 4 - Beta
Classifier: Intended Audience :: End Users/Desktop
Classifier: License :: OSI Approved :: MIT License
Classifier: Natural Language :: English
Classifier: Operating System :: Unix
Classifier: Programming Language :: Python :: 3 :: Only
